telosb/__init__.py
telosb/bsl.py
telosb/elf.py
telosb-1.39.dist-info/DESCRIPTION.rst
telosb-1.39.dist-info/METADATA
telosb-1.39.dist-info/RECORD
telosb-1.39.dist-info/WHEEL
telosb-1.39.dist-info/metadata.json
telosb-1.39.dist-info/top_level.txt
