Metadata-Version: 2.0
Name: telosb
Version: 1.39
Summary: Serial Bootstrap Loader software for the MSP430 embedded processor.
Home-page: https://github.com/sieben/telosb
Author: Rémy Léone
Author-email: remy.leone@gmail.com
License: ISC
Platform: UNKNOWN
Classifier: License :: OSI Approved :: MIT License
Classifier: Programming Language :: Python
Classifier: Programming Language :: Python :: 2.6
Classifier: Programming Language :: Python :: 2.7
Requires-Dist: pyserial
